LICENSE
MANIFEST.in
README.md
requirements.txt
setup.cfg
setup.py
playerpy/__init__.py
playerpy/__main__.py
playerpy/player.py
playerpy/version.py
playerpy.egg-info/PKG-INFO
playerpy.egg-info/SOURCES.txt
playerpy.egg-info/dependency_links.txt
playerpy.egg-info/entry_points.txt
playerpy.egg-info/requires.txt
playerpy.egg-info/top_level.txt
test/test_smoke.py