Metadata-Version: 1.1
Name: playerpy
Version: 0.1.1
Summary: Video player in python
Home-page: https://github.com/daniel-falk/playerpy
Author: Daniel Falk
Author-email: daniel.falk.1@fixedit.ai
License: MIT
Download-URL: https://github.com/daniel-falk/playerpy/archive/refs/tags/v0.1.1.tar.gz
Platform: UNKNOWN
